dolt_integrations/core/__init__.py
dolt_integrations/core/interface.py
dolt_integrations/dvc/examples/fashion-mnist/.gitignore
dolt_integrations/dvc/examples/fashion-mnist/dolt-dvc-demo.md
dolt_integrations/dvc/examples/fashion-mnist/train.py
dolt_integrations/metaflow/README.md
dolt_integrations/metaflow/__init__.py
dolt_integrations/metaflow/dolt.py
dolt_integrations/metaflow/examples/hospital_bounty/hospital_procedure_price_state_medians.py
dolt_integrations/metaflow/examples/hospital_bounty/hospital_procedure_price_variance_by_state.py
dolt_integrations/utils/__init__.py
dolt_integrations/utils/utils.py
dolt_integrations-0.1.5.dist-info/WHEEL
dolt_integrations-0.1.5.dist-info/METADATA
dolt_integrations-0.1.5.dist-info/RECORD
